setup.py
pygate/__init__.py
pygate/decorators.py
pygate/schemas.py
pygate/tasklet_decorators.py
pygate.egg-info/PKG-INFO
pygate.egg-info/SOURCES.txt
pygate.egg-info/dependency_links.txt
pygate.egg-info/top_level.txt
pygate.egg-info/zip-safe