Metadata-Version: 1.0
Name: pygate
Version: 0.1.2
Summary: Decorators and tools to 'gate' a function (check arguments and return values)
Home-page: UNKNOWN
Author: James Larsen
Author-email: somesocks@gmail.com
License: MIT
Platform: UNKNOWN
